aboo/__init__.py
aboo/aboo.py
aboo-0.0.0.dist-info/LICENSE
aboo-0.0.0.dist-info/METADATA
aboo-0.0.0.dist-info/WHEEL
aboo-0.0.0.dist-info/top_level.txt
aboo-0.0.0.dist-info/RECORD
