Metadata-Version: 2.1
Name: aboo
Version: 0.0.0
Summary: Banana API
Home-page: https://github.com/aphkyle/aboo
Author: aphkyle
Author-email: aphkyle@gmail.com
License: MIT
Platform: UNKNOWN
Classifier: License :: OSI Approved :: MIT License
Classifier: Programming Language :: Python :: 3
Classifier: Programming Language :: Python :: 3 :: Only
Classifier: Programming Language :: Python :: 3.7
Classifier: Programming Language :: Python :: 3.8
Classifier: Programming Language :: Python :: 3.9
Classifier: Programming Language :: Python :: Implementation :: CPython
Requires-Python: >3.6
License-File: LICENSE
